sampy/__init__.py
sampy/addons/__init__.py
sampy/addons/GIS_interface/__init__.py
sampy/addons/GIS_interface/geographic_grid.py
sampy/addons/GIS_interface/jit_compiled_functions.py
sampy/addons/ORM_related_addons/ORM_like_agents.py
sampy/addons/ORM_related_addons/__init__.py
sampy/addons/ORM_related_addons/graph_from_ORM_xml.py
sampy/addons/ORM_related_addons/jit_compiled_function.py
sampy/agent/__init__.py
sampy/agent/base.py
sampy/agent/builtin_agent.py
sampy/agent/jit_compiled_functions.py
sampy/agent/mortality.py
sampy/agent/movement.py
sampy/agent/random_walk.py
sampy/agent/reproduction.py
sampy/data_processing/__init__.py
sampy/data_processing/csv_manager.py
sampy/data_processing/extract_data_for_SCRW.py
sampy/data_processing/jit_compiled_functions.py
sampy/data_processing/write_file.py
sampy/disease/__init__.py
sampy/disease/single_species/__init__.py
sampy/disease/single_species/base.py
sampy/disease/single_species/builtin_disease.py
sampy/disease/single_species/jit_compiled_functions.py
sampy/disease/single_species/transition.py
sampy/disease/single_species/transmission.py
sampy/disease/two_species/__init__.py
sampy/disease/two_species/base.py
sampy/disease/two_species/builtin_disease.py
sampy/disease/two_species/jit_compiled_functions.py
sampy/disease/two_species/transition.py
sampy/disease/two_species/transmission.py
sampy/graph/__init__.py
sampy/graph/builtin_graph.py
sampy/graph/from_files.py
sampy/graph/jit_compiled_functions.py
sampy/graph/misc.py
sampy/graph/spatial_2d.py
sampy/graph/spatial_functions.py
sampy/graph/topology.py
sampy/graph/vertex_attributes.py
sampy/intervention/__init__.py
sampy/intervention/built_in_interventions.py
sampy/intervention/culling.py
sampy/intervention/jit_compiled_functions.py
sampy/intervention/sampling.py
sampy/intervention/vaccination.py
sampy/pandas_xs/__init__.py
sampy/pandas_xs/jit_compiled_functions.py
sampy/pandas_xs/pandas_xs.py
sampy/spatial/__init__.py
sampy/spatial/base_graph_intersection.py
sampy_abm-1.0.3.dist-info/LICENSE
sampy_abm-1.0.3.dist-info/METADATA
sampy_abm-1.0.3.dist-info/WHEEL
sampy_abm-1.0.3.dist-info/top_level.txt
sampy_abm-1.0.3.dist-info/RECORD
