Metadata-Version: 2.1
Name: sampy-abm
Version: 1.0.3
Summary: Library for ABM development in epidemiology.
Author-email: Francois Viard <sampy.project@gmail.com>
Project-URL: Homepage, https://github.com/sampy-project/sampy-main
Project-URL: Bug Tracker, https://github.com/sampy-project/sampy-main/issues
Requires-Python: >=3.8
License-File: LICENSE
Requires-Dist: numpy >=1.22
Requires-Dist: scipy >=1.8
Requires-Dist: pandas >=1.4.3
Requires-Dist: numba >=0.55.2
Requires-Dist: geojson >=3.1.0
